{
  "pdf_path": "C:\\RL\\RL_valid_pdf\\simpler\\UMS025.pdf",
  "full_document": "AN IMPORTANT UPDATE\nTO YOUR PLAN\nTaking money out\nIncluded with this letter:\nPrivate and confidential\nMr TDMjmfC UATjmfC\nAvenue Street\nP45\nLondon\nW2 4BA UMS025/289733/1/0\n29 November 2025 Customer ID: 7700049486\nTDMjmfC UATjmfC, we've changed your plan Got a question about\nyour savings?\nGive us a call:\nUsing your pension plan 1000059054L you have decided to:\n0345 266 9336\nLines are open\n· Take a taxable lump sum Mon - Fri 8am - 6pm\n· Fully cash in your plan\nWrite to us:\nirservicing\nYour cash payment\n@royallondon.com\nIncome Release\nRoyal London House\nAlderley Park, Congleton\nRoad\nPlan value Cash withdrawal Plan value after withdrawal\nNether Alderley\n£190,664.73\n£190,664.73 £0.00 Macclesfield\nDetails correct as of SK10 4EL\n27/11/2025\nAccess your plan online:\nhttps://\nwww.royallondon.com/\nlogin\nWe'll make a taxable cash payment to you of £190,664.73. Go to\nhmrc.gov.uk if you need more information about tax. This money less any\nLooking for some\ntax deducted should arrive in your bank account within the next five working\ndays. advice?\nTalk to your financial\nHow your plan has changed\nadviser:\nPerennial Financial\nEnclosed is a P45 confirming the tax we've paid to HMRC on your behalf in\nManagement Limited\nrespect of your final cash payment.\nHftsnvty Ynvjw\nXysynpx Yttspntt Hfyk\nWyrvt Yhvtsv\nCpzzmdrkqd\nDB7 1TT\nKnow your limits\nUnder UK pension rules there are limits on the amount of tax-free cash you\ncan access from your pension plan. The Lump Sum Allowance (LSA) is set\nat £268,275.00 and payments above this are subject to tax at your marginal\nrate of income tax. If you'd like more details about these allowances, please\nvisit royallondon.com/pensionallowances.\nYou've triggered the Money Purchase Annual Allowance (MPAA). The\ncurrent MPAA is £10,000.00 each year. If you contribute more than this\ninto any pension you'll be liable to a tax charge. Please note that within 91\ndays you must tell any other providers of plans or schemes to which you\ncontribute, that the MPAA trigger applies to you from 26 November 2025.\nCan I change my mind?\nYou have 30 days from the date of this letter to change your mind. All you\nneed to do is confirm you'd like to change your mind by writing to us at the\naddress shown.\nIncome Release\nRoyal London House\nAlderley Park, Congleton Road\nNether Alderley\nMacclesfield\nSK10 4EL\nYou'll need to pay back all the money we have paid you in full, before we will\nbe able to cancel your request. We'll reinvest this money back into your plan.\nWe're here to help\nAfter the payment is made, your plan with us will be closed. We'd like to take\nthis opportunity to say thanks for choosing to save with Royal London. Of\ncourse, if there's anything further we can do to help, please get in touch.\nYours sincerely\nRichard Basham-Jones\nHead of Customer Experience\n\nWe're happy to provide your documents in a different format, such\nas Braille, large print or audio, just ask us when you get in touch.\nAll our printed products are produced on stock which is from FSC® certified forests.\nThe Royal London Mutual Insurance Society Limited is authorised by the Prudential Regulation Authority and regulated by the Financial Conduct Authority\nand the Prudential Regulation Authority. The firm is on the Financial Services Register, registration number 117672. It provides life assurance and pensions.\nRegistered in England and Wales number 99064. Registered office: 80 Fenchurch Street, London, EC3M 4BY. Royal London Marketing Limited is authorised\nand regulated by the Financial Conduct Authority and introduces Royal London's customers to other insurance companies. The firm is on the Financial Services\nRegister, registration number 302391. Registered in England and Wales number 4414137. Registered office: 80 Fenchurch Street, London, EC3M 4BY.\nUMS025/289733/1/0\nP45 Part 1A\nDetails of employee leaving work\nCopy for employee\n1 Employer PAYE reference 5 Student Loan deductions\nOffice number Reference number\nStudent Loan deductions to continue\n120 / ME60530\n6 Tax code at leaving date\n2 Employee's National Insurance number\n1250L\nWM764243B\nIf week 1 or month 1 applies, enter 'X' in the box below.\n3 Title - enter MR, MRS, MISS, MS or other title Week 1/month 1\nMR\n7 Last entries on Payroll record/Deductions Working Sheet.\nComplete only if tax code is cumulative. If there is an 'X'\nSurname or family name\nat box 6 there will be no entries here.\nUATJMFC\n8\nWeek number Month number\nFirst name(s)\nTDMJMFC\nTotal pay to date\n£ 193,164.73 p\n4 Leaving date DD MM YYYY\nTotal tax to date\n27 11 2025\n£ 85,305.15 p\n8 This employment pay and tax. If no entry here, the amounts 12 Employee’s private address\nare those shown at box 7.\nTotal pay in this employment\nAVENUE STREET\n£ p LONDON\nTotal tax in this employment\n£ p Postcode\nW2 4BA\n9 Works number/Payroll number and Department or branch\n(if any) 13 I certify that the details entered in items 1 to 11 on\nthis form are correct.\n100058708/H29540 Employer name and address\nINCOME RELEASE\nROYAL LONDON HOUSE\n10 Gender. Enter 'X' in the appropriate box\nALDERLEY PARK, CONGLETON ROAD\nX NETHER ALDERLEY\nMale Female\nMACCLESFIELD\n11 Date of birth DD MM YYYY Postcode\n01 01 1995 SK10 4EL\nDate DD MM YYYY\n29 11 2025\nTo the employee Tax credits and Universal Credit\nThe P45 is in 3 parts. Please keep this part (Part 1A) safe. Tax credits and Universal Credit are flexible. They adapt to changes\nCopies are not available. You might need the information in in your life, such as leaving a job. If you need to let us know about a\nPart 1A to fill in a tax return if you are sent one. change in your income, phone 0345 300 3900.\nPlease read the notes in Part 2 that accompany Part 1A. To the new employer\nThe notes give some important information about what you\nshould do next and what you should do with Parts 2 and 3 of If your new employee gives you this Part 1A, please return it to\nthis form. them. Check the information on Parts 2 and 3 of this form is correct\nand transfer the information onto the Payroll record/Deductions\nWorking Sheet.\nP45(Continuous) Part 1A Page 1 HMRC 12/15\nP45 Part 2\nDetails of employee leaving work\nCopy for new employer\n1 Employer PAYE reference 5 Student Loan deductions\nOffice number Reference number\nStudent Loan deductions to continue\n120 / ME60530\n6 Tax code at leaving date\n2 Employee's National Insurance number\n1250L\nWM764243B\nIf week 1 or month 1 applies, enter 'X' in the box below.\n3 Title - enter MR, MRS, MISS, MS or other title Week 1/month 1\nMR\n7 Last entries on Payroll record/Deductions Working Sheet.\nComplete only if tax code is cumulative. If there is an 'X'\nSurname or family name\nat box 6 there will be no entries here.\nUATJMFC\n8\nWeek number Month number\nFirst name(s)\nTDMJMFC\nTotal pay to date\n£ 193,164.73 p\n4 Leaving date DD MM YYYY\nTotal tax to date\n27 11 2025\n£ 85,305.15 p\nTo the employee\nThis form is important to you. Take good care of it Claiming Jobseeker's Allowance or\nand keep it safe. Copies are not available. Please keep Employment and Support Allowance (ESA)\nParts 2 and 3 of the form together and do not alter them\nTake this form to your Jobcentre Plus office. They will pay you\nin any way.\nany tax refund you may be entitled to when your claim ends,\nGoing to a new job or at 5 April if this is earlier.\nGive Parts 2 and 3 of this form to your new employer, Not working and not claiming Jobseeker's Allowance or\nor you will have tax deducted using the emergency Employment and Support Allowance (ESA)\ncode and may pay too much tax. If you do not want\nIf you have paid tax and wish to claim a refund fill in\nyour new employer to know the details on this form,\nform P50, ‘Claiming tax back when you have stopped working’,\nsend it to your HM Revenue and Customs (HMRC) office\ngo to www.gov.uk/government/publications/income-tax-claiming-\nimmediately with a letter saying so and giving the\ntax-back-when-you-have-stopped-working-p50\nname and address of your new employer. HMRC can\nmake special arrangements, but you may pay too Help\nmuch tax for a while as a result of this. If you need more help, go to www.gov.uk/topic/businesstax/paye\nGoing abroad To the new employer\nIf you are going abroad or returning to a country\nCheck this form, record the start date and report it to HMRC in the\noutside the UK fill in form P85, ‘Leaving the United Kingdom’, go to\nfirst Full Payment Submission for your Employee. Prepare a Payroll\nwww.gov.uk/government/publications/income-tax-leaving-the-\nrecord/Deductions Working Sheet. Follow the instructions at\nuk-getting-your-tax-right-p85\nwww.gov.uk/payroll-software\nKeep Part 2.\nBecoming self-employed\nYou must register with HMRC within 3 months of\nbecoming self-employed or you could incur a penalty.\nTo register as newly self-employed, go to\nwww.gov.uk/topic/business-tax/self-employed\nP45(Continuous) Part 2 Page 2 HMRC 12/15\nP45 Part 3\nNew employee details\nFor completion by new employer\nUse capital letters when completing this form\n1 Employer PAYE reference 5 Student Loan deductions\nOffice number Reference number\nStudent Loan deductions to continue\n120 / ME60530\n6 Tax code at leaving date\n2 Employee's National Insurance number\n1250L\nWM764243B\nIf week 1 or month 1 applies, enter 'X' in the box below.\n3 Title - enter MR, MRS, MISS, MS or other title Week 1/month 1\nMR\n7 Last entries on Payroll record/Deductions Working Sheet.\nComplete only if tax code is cumulative. If there is an 'X'\nSurname or family name\nat box 6 there will be no entries here.\nUATJMFC\n8\nWeek number Month number\nFirst name(s)\nTDMJMFC\nTotal pay to date\n£ 193,164.73 p\n4 Leaving date DD MM YYYY\nTotal tax to date\n27 11 2025\n£ 85,305.15 p\nTo the new employer\n8 New employer PAYE reference 15 Employee's private address\nOffice number Reference number\n/\n9 Date new employment started DD MM YYYY\nPostcode\n10 Works number/Payroll number and Department or branch\n(if any)\n16 Gender. Enter 'X' in the appropriate box\nMale Female\n17 Date of birth DD MM YYYY\n11 Enter 'P' here if employee will not be paid by you\nbetween the date employment began and the\nnext 5 April.\nDeclaration\n12 Enter tax code in use if different to the tax code at box 6.\n18 I have prepared a Payroll record/Deductions Working\nSheet in accordance with the details above.\nEmployer name and address\nIf week 1 or month 1 applies, enter 'X' in the box below.\nWeek 1/month 1\n13 If the tax figure you are entering on the Payroll\nrecord/Deductions Working Sheet differs from box 7\nplease enter the figure here.\n£ p Postcode\n14 New employee's job title or job description Date DD MM YYYY\nP45(Continuous) Part 3 Page 3 HMRC 12/15",
  "headers_global": {
    "Title": "MR",
    "Surname": "UATjmfC",
    "First Name": "TDMjmfC",
    "Address": "Avenue Street",
    "City": "London",
    "Postcode": "W2 4BA",
    "Date 1": "29 November 2025",
    "Date 2": "26 November 2025",
    "Customer ID": "7700049486",
    "Pension Plan": "1000059054L",
    "Plan Value": "190,664.73",
    "Cash Withdrawal": "190,664.73",
    "Plan Value Post Withdrawal": "0.00",
    "Date 3": "27/11/2025",
    "NI Number": "WM764243B",
    "Leaving Date": "27 11 2025",
    "Tax Code": "1250L",
    "Total Pay to Date": "193,164.73",
    "Total Tax to Date": "85,305.15",
    "Date of Birth": "01 01 1995",
    "Month Number": "8"
  },
  "pages": [
    {
      "page_number": 1,
      "full_text": "AN IMPORTANT UPDATE\nTO YOUR PLAN\nTaking money out\nIncluded with this letter:\nPrivate and confidential\nMr TDMjmfC UATjmfC\nAvenue Street\nP45\nLondon\nW2 4BA UMS025/289733/1/0\n29 November 2025 Customer ID: 7700049486\nTDMjmfC UATjmfC, we've changed your plan Got a question about\nyour savings?\nGive us a call:\nUsing your pension plan 1000059054L you have decided to:\n0345 266 9336\nLines are open\n· Take a taxable lump sum Mon - Fri 8am - 6pm\n· Fully cash in your plan\nWrite to us:\nirservicing\nYour cash payment\n@royallondon.com\nIncome Release\nRoyal London House\nAlderley Park, Congleton\nRoad\nPlan value Cash withdrawal Plan value after withdrawal\nNether Alderley\n£190,664.73\n£190,664.73 £0.00 Macclesfield\nDetails correct as of SK10 4EL\n27/11/2025\nAccess your plan online:\nhttps://\nwww.royallondon.com/\nlogin\nWe'll make a taxable cash payment to you of £190,664.73. Go to\nhmrc.gov.uk if you need more information about tax. This money less any\nLooking for some\ntax deducted should arrive in your bank account within the next five working\ndays. advice?\nTalk to your financial\nHow your plan has changed\nadviser:\nPerennial Financial\nEnclosed is a P45 confirming the tax we've paid to HMRC on your behalf in\nManagement Limited\nrespect of your final cash payment.\nHftsnvty Ynvjw\nXysynpx Yttspntt Hfyk\nWyrvt Yhvtsv\nCpzzmdrkqd\nDB7 1TT",
      "headers": {
        "Title": "MR",
        "Surname": "UATjmfC",
        "First Name": "TDMjmfC",
        "Address": "Avenue Street",
        "City": "London",
        "Postcode": "W2 4BA",
        "Date 1": "29 November 2025",
        "Customer ID": "7700049486",
        "Pension Plan": "1000059054L",
        "Plan Value": "190,664.73",
        "Cash Withdrawal": "190,664.73",
        "Plan Value Post Withdrawal": "0.00",
        "Date 3": "27/11/2025",
        "Month Number": "8"
      }
    },
    {
      "page_number": 2,
      "full_text": "Know your limits\nUnder UK pension rules there are limits on the amount of tax-free cash you\ncan access from your pension plan. The Lump Sum Allowance (LSA) is set\nat £268,275.00 and payments above this are subject to tax at your marginal\nrate of income tax. If you'd like more details about these allowances, please\nvisit royallondon.com/pensionallowances.\nYou've triggered the Money Purchase Annual Allowance (MPAA). The\ncurrent MPAA is £10,000.00 each year. If you contribute more than this\ninto any pension you'll be liable to a tax charge. Please note that within 91\ndays you must tell any other providers of plans or schemes to which you\ncontribute, that the MPAA trigger applies to you from 26 November 2025.\nCan I change my mind?\nYou have 30 days from the date of this letter to change your mind. All you\nneed to do is confirm you'd like to change your mind by writing to us at the\naddress shown.\nIncome Release\nRoyal London House\nAlderley Park, Congleton Road\nNether Alderley\nMacclesfield\nSK10 4EL\nYou'll need to pay back all the money we have paid you in full, before we will\nbe able to cancel your request. We'll reinvest this money back into your plan.\nWe're here to help\nAfter the payment is made, your plan with us will be closed. We'd like to take\nthis opportunity to say thanks for choosing to save with Royal London. Of\ncourse, if there's anything further we can do to help, please get in touch.\nYours sincerely\nRichard Basham-Jones\nHead of Customer Experience",
      "headers": {
        "City": "London",
        "Date 2": "26 November 2025",
        "Plan Value Post Withdrawal": "0.00",
        "Month Number": "8"
      }
    },
    {
      "page_number": 3,
      "full_text": "",
      "headers": {}
    },
    {
      "page_number": 4,
      "full_text": "We're happy to provide your documents in a different format, such\nas Braille, large print or audio, just ask us when you get in touch.\nAll our printed products are produced on stock which is from FSC® certified forests.\nThe Royal London Mutual Insurance Society Limited is authorised by the Prudential Regulation Authority and regulated by the Financial Conduct Authority\nand the Prudential Regulation Authority. The firm is on the Financial Services Register, registration number 117672. It provides life assurance and pensions.\nRegistered in England and Wales number 99064. Registered office: 80 Fenchurch Street, London, EC3M 4BY. Royal London Marketing Limited is authorised\nand regulated by the Financial Conduct Authority and introduces Royal London's customers to other insurance companies. The firm is on the Financial Services\nRegister, registration number 302391. Registered in England and Wales number 4414137. Registered office: 80 Fenchurch Street, London, EC3M 4BY.\nUMS025/289733/1/0",
      "headers": {
        "City": "London",
        "Month Number": "8"
      }
    },
    {
      "page_number": 5,
      "full_text": "P45 Part 1A\nDetails of employee leaving work\nCopy for employee\n1 Employer PAYE reference 5 Student Loan deductions\nOffice number Reference number\nStudent Loan deductions to continue\n120 / ME60530\n6 Tax code at leaving date\n2 Employee's National Insurance number\n1250L\nWM764243B\nIf week 1 or month 1 applies, enter 'X' in the box below.\n3 Title - enter MR, MRS, MISS, MS or other title Week 1/month 1\nMR\n7 Last entries on Payroll record/Deductions Working Sheet.\nComplete only if tax code is cumulative. If there is an 'X'\nSurname or family name\nat box 6 there will be no entries here.\nUATJMFC\n8\nWeek number Month number\nFirst name(s)\nTDMJMFC\nTotal pay to date\n£ 193,164.73 p\n4 Leaving date DD MM YYYY\nTotal tax to date\n27 11 2025\n£ 85,305.15 p\n8 This employment pay and tax. If no entry here, the amounts 12 Employee’s private address\nare those shown at box 7.\nTotal pay in this employment\nAVENUE STREET\n£ p LONDON\nTotal tax in this employment\n£ p Postcode\nW2 4BA\n9 Works number/Payroll number and Department or branch\n(if any) 13 I certify that the details entered in items 1 to 11 on\nthis form are correct.\n100058708/H29540 Employer name and address\nINCOME RELEASE\nROYAL LONDON HOUSE\n10 Gender. Enter 'X' in the appropriate box\nALDERLEY PARK, CONGLETON ROAD\nX NETHER ALDERLEY\nMale Female\nMACCLESFIELD\n11 Date of birth DD MM YYYY Postcode\n01 01 1995 SK10 4EL\nDate DD MM YYYY\n29 11 2025\nTo the employee Tax credits and Universal Credit\nThe P45 is in 3 parts. Please keep this part (Part 1A) safe. Tax credits and Universal Credit are flexible. They adapt to changes\nCopies are not available. You might need the information in in your life, such as leaving a job. If you need to let us know about a\nPart 1A to fill in a tax return if you are sent one. change in your income, phone 0345 300 3900.\nPlease read the notes in Part 2 that accompany Part 1A. To the new employer\nThe notes give some important information about what you\nshould do next and what you should do with Parts 2 and 3 of If your new employee gives you this Part 1A, please return it to\nthis form. them. Check the information on Parts 2 and 3 of this form is correct\nand transfer the information onto the Payroll record/Deductions\nWorking Sheet.\nP45(Continuous) Part 1A Page 1 HMRC 12/15",
      "headers": {
        "Title": "MR",
        "Surname": "UATjmfC",
        "First Name": "TDMjmfC",
        "Address": "Avenue Street",
        "City": "London",
        "Postcode": "W2 4BA",
        "NI Number": "WM764243B",
        "Leaving Date": "27 11 2025",
        "Tax Code": "1250L",
        "Total Pay to Date": "193,164.73",
        "Total Tax to Date": "85,305.15",
        "Date of Birth": "01 01 1995",
        "Month Number": "8"
      }
    },
    {
      "page_number": 6,
      "full_text": "P45 Part 2\nDetails of employee leaving work\nCopy for new employer\n1 Employer PAYE reference 5 Student Loan deductions\nOffice number Reference number\nStudent Loan deductions to continue\n120 / ME60530\n6 Tax code at leaving date\n2 Employee's National Insurance number\n1250L\nWM764243B\nIf week 1 or month 1 applies, enter 'X' in the box below.\n3 Title - enter MR, MRS, MISS, MS or other title Week 1/month 1\nMR\n7 Last entries on Payroll record/Deductions Working Sheet.\nComplete only if tax code is cumulative. If there is an 'X'\nSurname or family name\nat box 6 there will be no entries here.\nUATJMFC\n8\nWeek number Month number\nFirst name(s)\nTDMJMFC\nTotal pay to date\n£ 193,164.73 p\n4 Leaving date DD MM YYYY\nTotal tax to date\n27 11 2025\n£ 85,305.15 p\nTo the employee\nThis form is important to you. Take good care of it Claiming Jobseeker's Allowance or\nand keep it safe. Copies are not available. Please keep Employment and Support Allowance (ESA)\nParts 2 and 3 of the form together and do not alter them\nTake this form to your Jobcentre Plus office. They will pay you\nin any way.\nany tax refund you may be entitled to when your claim ends,\nGoing to a new job or at 5 April if this is earlier.\nGive Parts 2 and 3 of this form to your new employer, Not working and not claiming Jobseeker's Allowance or\nor you will have tax deducted using the emergency Employment and Support Allowance (ESA)\ncode and may pay too much tax. If you do not want\nIf you have paid tax and wish to claim a refund fill in\nyour new employer to know the details on this form,\nform P50, ‘Claiming tax back when you have stopped working’,\nsend it to your HM Revenue and Customs (HMRC) office\ngo to www.gov.uk/government/publications/income-tax-claiming-\nimmediately with a letter saying so and giving the\ntax-back-when-you-have-stopped-working-p50\nname and address of your new employer. HMRC can\nmake special arrangements, but you may pay too Help\nmuch tax for a while as a result of this. If you need more help, go to www.gov.uk/topic/businesstax/paye\nGoing abroad To the new employer\nIf you are going abroad or returning to a country\nCheck this form, record the start date and report it to HMRC in the\noutside the UK fill in form P85, ‘Leaving the United Kingdom’, go to\nfirst Full Payment Submission for your Employee. Prepare a Payroll\nwww.gov.uk/government/publications/income-tax-leaving-the-\nrecord/Deductions Working Sheet. Follow the instructions at\nuk-getting-your-tax-right-p85\nwww.gov.uk/payroll-software\nKeep Part 2.\nBecoming self-employed\nYou must register with HMRC within 3 months of\nbecoming self-employed or you could incur a penalty.\nTo register as newly self-employed, go to\nwww.gov.uk/topic/business-tax/self-employed\nP45(Continuous) Part 2 Page 2 HMRC 12/15",
      "headers": {
        "Title": "MR",
        "Surname": "UATjmfC",
        "First Name": "TDMjmfC",
        "NI Number": "WM764243B",
        "Leaving Date": "27 11 2025",
        "Tax Code": "1250L",
        "Total Pay to Date": "193,164.73",
        "Total Tax to Date": "85,305.15",
        "Month Number": "8"
      }
    },
    {
      "page_number": 7,
      "full_text": "P45 Part 3\nNew employee details\nFor completion by new employer\nUse capital letters when completing this form\n1 Employer PAYE reference 5 Student Loan deductions\nOffice number Reference number\nStudent Loan deductions to continue\n120 / ME60530\n6 Tax code at leaving date\n2 Employee's National Insurance number\n1250L\nWM764243B\nIf week 1 or month 1 applies, enter 'X' in the box below.\n3 Title - enter MR, MRS, MISS, MS or other title Week 1/month 1\nMR\n7 Last entries on Payroll record/Deductions Working Sheet.\nComplete only if tax code is cumulative. If there is an 'X'\nSurname or family name\nat box 6 there will be no entries here.\nUATJMFC\n8\nWeek number Month number\nFirst name(s)\nTDMJMFC\nTotal pay to date\n£ 193,164.73 p\n4 Leaving date DD MM YYYY\nTotal tax to date\n27 11 2025\n£ 85,305.15 p\nTo the new employer\n8 New employer PAYE reference 15 Employee's private address\nOffice number Reference number\n/\n9 Date new employment started DD MM YYYY\nPostcode\n10 Works number/Payroll number and Department or branch\n(if any)\n16 Gender. Enter 'X' in the appropriate box\nMale Female\n17 Date of birth DD MM YYYY\n11 Enter 'P' here if employee will not be paid by you\nbetween the date employment began and the\nnext 5 April.\nDeclaration\n12 Enter tax code in use if different to the tax code at box 6.\n18 I have prepared a Payroll record/Deductions Working\nSheet in accordance with the details above.\nEmployer name and address\nIf week 1 or month 1 applies, enter 'X' in the box below.\nWeek 1/month 1\n13 If the tax figure you are entering on the Payroll\nrecord/Deductions Working Sheet differs from box 7\nplease enter the figure here.\n£ p Postcode\n14 New employee's job title or job description Date DD MM YYYY\nP45(Continuous) Part 3 Page 3 HMRC 12/15",
      "headers": {
        "Title": "MR",
        "Surname": "UATjmfC",
        "First Name": "TDMjmfC",
        "NI Number": "WM764243B",
        "Leaving Date": "27 11 2025",
        "Tax Code": "1250L",
        "Total Pay to Date": "193,164.73",
        "Total Tax to Date": "85,305.15",
        "Month Number": "8"
      }
    }
  ]
}